{"entities": {"Q41419": {"pageid": 43705, "ns": 0, "title": "Q41419", "lastrevid": 2373647289, "modified": "2025-07-04T23:49:33Z", "type": "item", "id": "Q41419", "labels": {"lb": {"language": "lb", "value": "Hestia"}, "zh": {"language": "zh", "value": "\u8d6b\u65af\u63d0\u4e9e"}, "eu": {"language": "eu", "value": "Hestia"}, "pl": {"language": "pl", "value": "Hestia"}, "bs": {"language": "bs", "value": "Hestija"}, "es": {"language": "es", "value": "Hestia"}, "ta": {"language": "ta", "value": "\u0bb9\u0bc6\u0bb8\u0bcd\u0b9f\u0bbf\u0baf\u0bbe"}, "af": {"language": "af", "value": "Hestia"}, "oc": {"language": "oc", "value": "Estia"}, "hu": {"language": "hu", "value": "Hesztia"}, "sw": {"language": "sw", "value": "Hestia"}, "et": {"language": "et", "value": "Hestia"}, "bn": {"language": "bn", "value": "\u09b9\u09c7\u09b8\u09cd\u09a4\u09bf\u09af\u09bc\u09be"}, "br": {"language": "br", "value": "Hestia"}, "sq": {"language": "sq", "value": "Hestia"}, "el": {"language": "el", "value": "\u0395\u03c3\u03c4\u03af\u03b1"}, "ia": {"language": "ia", "value": "Hestia"}, "ar": {"language": "ar", "value": "\u0647\u064a\u0633\u062a\u064a\u0627"}, "sv": {"language": "sv", "value": "Hestia"}, "nl": {"language": "nl", "value": "Hestia"}, "pt": {"language": "pt", "value": "H\u00e9stia"}, "eo": {"language": "eo", "value": "Hestia"}, "ru": {"language": "ru", "value": "\u0413\u0435\u0441\u0442\u0438\u044f"}, "ast": {"language": "ast", "value": "Hestia"}, "sr": {"language": "sr", "value": "\u0425\u0435\u0441\u0442\u0438\u0458\u0430"}, "tr": {"language": "tr", "value": "Hestia"}, "mk": {"language": "mk", "value": "\u0425\u0435\u0441\u0442\u0438\u0458\u0430"}, "fi": {"language": "fi", "value": "Hestia"}, "uk": {"language": "uk", "value": "\u0413\u0435\u0441\u0442\u0456\u044f"}, "pa": {"language": "pa", "value": "\u0a39\u0a47\u0a38\u0a1f\u0a40\u0a06"}, "mzn": {"language": "mzn", "value": "\u0647\u0633\u062a\u06cc\u0627"}, "hr": {"language": "hr", "value": "Hestija"}, "az": {"language": "az", "value": "Hestiya"}, "tl": {"language": "tl", "value": "Hestia"}, "an": {"language": "an", "value": "Hestia"}, "da": {"language": "da", "value": "Hestia"}, "ko": {"language": "ko", "value": "\ud5e4\uc2a4\ud2f0\uc544"}, "he": {"language": "he", "value": "\u05d4\u05e1\u05d8\u05d9\u05d4"}, "fr": {"language": "fr", "value": "Hestia"}, "be": {"language": "be", "value": "\u0413\u0435\u0441\u0442\u044b\u044f"}, "arz": {"language": "arz", "value": "\u0647\u064a\u0633\u062a\u064a\u0627"}, "bar": {"language": "bar", "value": "Hestia"}, "lv": {"language": "lv", "value": "Hestija"}, "it": {"language": "it", "value": "Estia"}, "gl": {"language": "gl", "value": "Hestia"}, "id": {"language": "id", "value": "Hestia"}, "de": {"language": "de", "value": "Hestia"}, "ja": {"language": "ja", "value": "\u30d8\u30b9\u30c6\u30a3\u30a2\u30fc"}, "ml": {"language": "ml", "value": "\u0d39\u0d46\u0d38\u0d4d\u0d31\u0d4d\u0d31\u0d3f\u0d2f"}, "vi": {"language": "vi", "value": "Hestia"}, "en": {"language": "en", "value": "Hestia"}, "sh": {"language": "sh", "value": "Hestija"}, "hi": {"language": "hi", "value": "\u0939\u0947\u0938\u094d\u091f\u093f\u092f\u093e"}, "sk": {"language": "sk", "value": "Hestia"}, "hy": {"language": "hy", "value": "\u0540\u0565\u057d\u057f\u056b\u0561"}, "ro": {"language": "ro", "value": "Hestia"}, "th": {"language": "th", "value": "\u0e40\u0e2e\u0e2a\u0e40\u0e15\u0e35\u0e22"}, "ca": {"language": "ca", "value": "H\u00e8stia"}, "la": {"language": "la", "value": "Hestia"}, "cy": {"language": "cy", "value": "Hestia"}, "sl": {"language": "sl", "value": "Hestija"}, "war": {"language": "war", "value": "Hestia"}, "cs": {"language": "cs", "value": "Hestia"}, "mr": {"language": "mr", "value": "\u0939\u0947\u0938\u094d\u0924\u093f\u092f\u093e"}, "bg": {"language": "bg", "value": "\u0425\u0435\u0441\u0442\u0438\u044f"}, "fa": {"language": "fa", "value": "\u0647\u0633\u062a\u06cc\u0627"}, "ka": {"language": "ka", "value": "\u10f0\u10d4\u10e1\u10e2\u10d8\u10d0"}, "nds": {"language": "nds", "value": "Hestia"}, "lt": {"language": "lt", "value": "Hestija"}, "jv": {"language": "jv", "value": "Hestia"}, "nn": {"language": "nn", "value": "Hestia"}, "nb": {"language": "nb", "value": "Hestia"}, "ur": {"language": "ur", "value": "\u06c1\u06cc\u0633\u0679\u06cc\u06c1"}, "be-tarask": {"language": "be-tarask", "value": "\u0413\u0435\u0441\u0442\u044b\u044f"}, "sco": {"language": "sco", "value": "Hestia"}, "kk": {"language": "kk", "value": "\u0413\u0435\u0441\u0442\u0438\u044f"}, "tt": {"language": "tt", "value": "Hesti\u00e4"}, "ga": {"language": "ga", "value": "Heistia"}, "vep": {"language": "vep", "value": "Gestija"}, "nan": {"language": "nan", "value": "Hestia"}, "grc": {"language": "grc", "value": "\u1f19\u03c3\u03c4\u03af\u03b1"}, "wuu": {"language": "wuu", "value": "\u8d6b\u65af\u63d0\u4e9a"}, "yue": {"language": "yue", "value": "\u8d6b\u65af\u63d0\u4e9e"}, "lfn": {"language": "lfn", "value": "Hestia"}, "pnb": {"language": "pnb", "value": "\u06c1\u06cc\u0633\u0679\u06cc\u06c1"}, "mni": {"language": "mni", "value": "\uabcd\uabe6\uabc1\uabed\uabc7\uabe4\uabcc\uabe5"}, "as": {"language": "as", "value": "\u09b9\u09c7\u09b7\u09cd\u099f\u09bf\u09af\u09bc\u09be"}, "ku-latn": {"language": "ku-latn", "value": "Hest\u00eea"}, "ku": {"language": "ku", "value": "Hest\u00eea"}, "uz": {"language": "uz", "value": "Xestiya"}, "hyw": {"language": "hyw", "value": "\u0537\u057d\u0569\u056b\u0561"}, "io": {"language": "io", "value": "Hestia"}, "sr-ec": {"language": "sr-ec", "value": "\u0425\u0435\u0441\u0442\u0438\u0458\u0430"}, "sr-el": {"language": "sr-el", "value": "Hestija"}, "en-us": {"language": "en-us", "value": "Hestia"}, "bcl": {"language": "bcl", "value": "Hestia"}, "zh-tw": {"language": "zh-tw", "value": "\u8d6b\u65af\u63d0\u4e9e"}, "ms": {"language": "ms", "value": "Hestia"}}, "descriptions": {"nl": {"language": "nl", "value": "godin van het haardvuur in de Griekse mythologie"}, "es": {"language": "es", "value": "diosa griega del hogar"}, "de": {"language": "de", "value": "G\u00f6ttin des Herdfeuers in der griechischen Mythologie"}, "en": {"language": "en", "value": "Greek goddess"}, "el": {"language": "el", "value": "\u03b8\u03b5\u03ac \u03c4\u03b7\u03c2 \u03b5\u03bb\u03bb\u03b7\u03bd\u03b9\u03ba\u03ae\u03c2 \u03bc\u03c5\u03b8\u03bf\u03bb\u03bf\u03b3\u03af\u03b1\u03c2"}, "ru": {"language": "ru", "value": "\u0432 \u0434\u0440\u0435\u0432\u043d\u0435\u0433\u0440\u0435\u0447\u0435\u0441\u043a\u043e\u0439 \u043c\u0438\u0444\u043e\u043b\u043e\u0433\u0438\u0438 \u044e\u043d\u0430\u044f \u0431\u043e\u0433\u0438\u043d\u044f \u0441\u0435\u043c\u0435\u0439\u043d\u043e\u0433\u043e \u043e\u0447\u0430\u0433\u0430 \u0438 \u0436\u0435\u0440\u0442\u0432\u0435\u043d\u043d\u043e\u0433\u043e \u043e\u0433\u043d\u044f"}, "ja": {"language": "ja", "value": "\u30ae\u30ea\u30b7\u30a2\u795e\u8a71\u306b\u767b\u5834\u3059\u308b\u7089\u306e\u5973\u795e"}, "fr": {"language": "fr", "value": "d\u00e9esse grecque antique du foyer"}, "ar": {"language": "ar", "value": "\u0631\u0628\u0629 \u0627\u0644\u0645\u0648\u0642\u062f \u0648\u0627\u0644\u0645\u0646\u0632\u0644 \u0648\u0627\u0644\u062d\u064a\u0627\u0629 \u0627\u0644\u0645\u0646\u0632\u0644\u064a\u0629 \u0648\u0627\u0644\u0623\u0633\u0631\u0629 \u0639\u0646\u062f \u0627\u0644\u0631\u0648\u0645\u0627\u0646"}, "pl": {"language": "pl", "value": "bogini w mitologii greckiej"}, "sk": {"language": "sk", "value": "gr\u00e9cka bohy\u0148a dom\u00e1ceho kozuba"}, "hu": {"language": "hu", "value": "A csal\u00e1di t\u0171zhely, az otthon \u00e9s a h\u00e1zias \u00e9let g\u00f6r\u00f6g istenn\u0151je"}, "it": {"language": "it", "value": "dea greca del focolare, della casa e della famiglia, figlia di Crono e Rea"}, "ro": {"language": "ro", "value": "zei\u021ba c\u0103minului \u00een mitologia greac\u0103"}, "bn": {"language": "bn", "value": "\u0997\u09cd\u09b0\u09c0\u0995 \u09a6\u09c7\u09ac\u09c0"}, "cs": {"language": "cs", "value": "\u0159eck\u00e1 bohyn\u011b dom\u00e1c\u00edho krbu"}, "fa": {"language": "fa", "value": "\u0628\u0632\u0631\u06af\u200c\u062a\u0631\u06cc\u0646 \u062e\u0648\u0627\u0647\u0631 \u0632\u0626\u0648\u0633"}, "id": {"language": "id", "value": "Dewi perapian dan keluarga"}, "tr": {"language": "tr", "value": "Yunan mitolojisinde tanr\u0131\u00e7a"}, "uk": {"language": "uk", "value": "\u0434\u0430\u0432\u043d\u044c\u043e\u0433\u0440\u0435\u0446\u044c\u043a\u0430 \u0431\u043e\u0433\u0438\u043d\u044f \u0432\u043e\u0433\u043d\u044e, \u043a\u0443\u043b\u0456\u043d\u0430\u0440\u0456\u0457 \u0442\u0430 \u043f\u0435\u043a\u0430\u0440\u0441\u0442\u0432\u0430"}, "ko": {"language": "ko", "value": "\uadf8\ub9ac\uc2a4 \uc2e0\ud654\uc758 \uc5ec\uc2e0"}, "ca": {"language": "ca", "value": "deesa ol\u00edmpica grega"}, "mni": {"language": "mni", "value": "\uabd2\uabed\uabd4\uabe4\uabdb\uabc0\uabe4 \uabd0\uabe8\uabe1\uabd2\uabe5 \uabc2\uabe5\uabe2\uabd4\uabe8\uabd2\uabe4 \uabc2\uabe5\uabe2\uabd4\uabe6\uabdd\uabd5\uabe4"}, "as": {"language": "as", "value": "\u0997\u09cd\u09f0\u09c0\u0995 \u09a6\u09c7\u09f1\u09c0"}, "he": {"language": "he", "value": "\u05d0\u05dc\u05ea \u05d4\u05d1\u05d9\u05ea, \u05d4\u05de\u05e9\u05e4\u05d7\u05d4 \u05d5\u05d0\u05e9 \u05d4\u05d0\u05d7 \u05d1\u05de\u05d9\u05ea\u05d5\u05dc\u05d5\u05d2\u05d9\u05d4 \u05d4\u05d9\u05d5\u05d5\u05e0\u05d9\u05ea"}, "hyw": {"language": "hyw", "value": "\u0575\u0578\u0575\u0576 \u0561\u057d\u057f\u0578\u0582\u0561\u056e\u0578\u0582\u0570\u056b"}, "sr-ec": {"language": "sr-ec", "value": "\u0433\u0440\u0447\u043a\u0430 \u0431\u043e\u0433\u0438\u045a\u0430"}, "sr-el": {"language": "sr-el", "value": "gr\u010dka boginja"}, "en-us": {"language": "en-us", "value": "Greek goddess"}, "lb": {"language": "lb", "value": "griichesch G\u00ebttin"}}, "aliases": {"zh": [{"language": "zh", "value": "\u8d6b\u65af\u63d0\u5a6d"}], "bn": [{"language": "bn", "value": "\u09b9\u09c7\u09b8\u09cd\u099f\u09bf\u09af\u09bc\u09be"}], "pt": [{"language": "pt", "value": "Hestia"}], "eo": [{"language": "eo", "value": "Hestio"}], "tl": [{"language": "tl", "value": "Hestya"}, {"language": "tl", "value": "Hestiya"}, {"language": "tl", "value": "Besta"}, {"language": "tl", "value": "Vesta"}], "fr": [{"language": "fr", "value": "H\u00e9stia"}], "ja": [{"language": "ja", "value": "\u30a8\u30b9\u30c6\u30a3\u30a2"}, {"language": "ja", "value": "\u30d8\u30b9\u30c6\u30a3\u30a2"}], "ml": [{"language": "ml", "value": "Hestia"}], "th": [{"language": "th", "value": "Hestia"}, {"language": "th", "value": "\u0e40\u0e2e\u0e2a\u0e40\u0e17\u0e35\u0e22"}], "ca": [{"language": "ca", "value": "Vesta"}], "la": [{"language": "la", "value": "\u0388\u03c3\u03c4\u03af\u03b1"}], "cs": [{"language": "cs", "value": "Hestie"}], "mr": [{"language": "mr", "value": "\u0939\u0947\u0938\u094d\u0924\u093f\u0906"}], "nds": [{"language": "nds", "value": "Vesta"}], "en": [{"language": "en", "value": "\u0395\u03a3\u03a4\u0399\u0391"}, {"language": "en", "value": "\u0395\u03c3\u03c4\u03af\u03b1"}, {"language": "en", "value": "Histia, Vesta"}], "grc": [{"language": "grc", "value": "\u0395\u03a3\u03a4\u0399\u0391"}, {"language": "grc", "value": "\u0395\u03c3\u03c4\u03af\u03b1"}], "mni": [{"language": "mni", "value": "\uabcd\uabe6\uabc1\uabc7\uabed\uabcc\uabe5"}], "as": [{"language": "as", "value": "\u09b9\u09bf\u09b7\u09cd\u099f\u09bf\u09af\u09bc\u09be"}], "sr-ec": [{"language": "sr-ec", "value": "\u1f19\u03c3\u03c4\u03af\u03b1"}], "sr-el": [{"language": "sr-el", "value": "\u1f19\u03c3\u03c4\u03af\u03b1"}], "en-us": [{"language": "en-us", "value": "E\u03c3\u03c4\u03af\u03b1"}]}, "claims": {"P373": [{"mainsnak": {"snaktype": "value", "property": "P373", "hash": "0b9bec1c20dd56e2d7337b077ab9e4e3eba95596", "datavalue": {"value": "Hestia", "type": "string"}, "datatype": "string"}, "type": "statement", "id": "q41419$84EF226F-3D03-4593-874F-31E3A18D1D80", "rank": "normal", "references": [{"hash": "fa278ebfc458360e5aed63d5058cca83c46134f1", "snaks": {"P143": [{"snaktype": "value", "property": "P143", "hash": "e4f6d9441d0600513c4533c672b5ab472dc73694", "datavalue": {"value": {"entity-type": "item", "numeric-id": 328, "id": "Q328"}, "type": "wikibase-entityid"}, "datatype": "wikibase-item"}]}, "snaks-order": ["P143"]}]}], "P21": [{"mainsnak": {"snaktype": "value", "property": "P21", "hash": "5760796ff6ebc63aae12cdcbf509b07ebf0bd201", "datavalue": {"value": {"entity-type": "item", "numeric-id": 6581072, "id": "Q6581072"}, "type": "wikibase-entityid"}, "datatype": "wikibase-item"}, "type": "statement", "id": "q41419$348e246e-40f7-9ced-5686-1b9671bbc1bd", "rank": "normal"}], "P22": [{"mainsnak": {"snaktype": "value", "property": "P22", "hash": "34f5126ea3f5499b285cdd672672539a3d277c4d", "datavalue": {"value": {"entity-type": "item", "numeric-id": 44204, "id": "Q44204"}, "type": "wikibase-entityid"}, "datatype": "wikibase-item"}, "type": "statement", "id": "q41419$1dec914f-41a4-68b6-30fb-e1e62349a5fb", "rank": "normal"}], "P25": [{"mainsnak": {"snaktype": "value", "property": "P25", "hash": "7a34069e7fb18158f24f4ecd31774ff713c4e04b", "datavalue": {"value": {"entity-type": "item", "numeric-id": 108419, "id": "Q108419"}, "type": "wikibase-entityid"}, "datatype": "wikibase-item"}, "type": "statement", "id": "q41419$7d0a43c2-40b3-3124-889b-0fdc0efbbb7f", "rank": "normal"}], "P227": [{"mainsnak": {"snaktype": "value", "property": "P227", "hash": "61efc47e1cbc62751d2e9ceabd78cdfbb720c10e", "datavalue": {"value": "119320657", "type": "string"}, "datatype": "external-id"}, "type": "statement", "id": "q41419$3DF5D2B4-AA1F-435B-B7F3-7494AC428E41", "rank": "normal", "references": [{"hash": "9a24f7c0208b05d6be97077d855671d1dfdbc0dd", "snaks": {"P143": [{"snaktype": "value", "property": "P143", "hash": "d38375ffe6fe142663ff55cd783aa4df4301d83d", "datavalue": {"value": {"entity-type": "item", "numeric-id": 48183, "id": "Q48183"}, "type": "wikibase-entityid"}, "datatype": "wikibase-item"}]}, "snaks-order": ["P143"]}]}], "P31": [{"mainsnak": {"snaktype": "value", "property": "P31", "hash": "9b9d8ea22320e79f4c8b3d70cdff49f311d2d7fc", "datavalue": {"value": {"entity-type": "item", "numeric-id": 22989102, "id": "Q22989102"}, "type": "wikibase-entityid"}, "datatype": "wikibase-item"}, "type": "statement", "id": "q41419$76f8e9cc-44ce-3dc9-4db1-49a443486eba", "rank": "normal"}, {"mainsnak": {"snaktype": "value", "property": "P31", "hash": "050ef0eb0f89634386170a292d48d2de3668ad44", "datavalue": {"value": {"entity-type": "item", "numeric-id": 30307677, "id": "Q30307677"}, "type": "wikibase-entityid"}, "datatype": "wikibase-item"}, "type": "statement", "id": "Q41419$2221ecd6-48ec-6d41-ce74-d05acc704990", "rank": "normal"}, {"mainsnak": {"snaktype": "value", "property": "P31", "hash": "843991238027f9006be64b035847d9b5854fcb30", "datavalue": {"value": {"entity-type": "item", "numeric-id": 113103481, "id": "Q113103481"}, "type": "wikibase-entityid"}, "datatype": "wikibase-item"}, "type": "statement", "id": "Q41419$A9D00FDC-A73D-43A6-B31A-A1B8E6310007", "rank": "normal", "references": [{"hash": "9f351242e7c7366da610a77dd4a667417aa3fa2a", "snaks": {"P854": [{"snaktype": "value", "property": "P854", "hash": "91457e8e766b9af737461c7150b5d667892dbb23", "datavalue": {"value": "https://greekmythology.fandom.com/wiki/Olympian?oldid=79128#First_Olympians", "type": "string"}, "datatype": "url"}], "P1476": [{"snaktype": "value", "property": "P1476", "hash": "e32aa88a243448fa7bd0e1581170acf822d31b45", "datavalue": {"value": {"text": "Olympian | Greek Mythology Wiki | Fandom", "language": "en"}, "type": "monolingualtext"}, "datatype": "monolingualtext"}], "P958": [{"snaktype": "value", "property": "P958", "hash": "479787051d175e9261de071bea11fb8262ae8007", "datavalue": {"value": "First Olympians", "type": "string"}, "datatype": "string"}]}, "snaks-order": ["P854", "P1476", "P958"]}]}], "P910": [{"mainsnak": {"snaktype": "value", "property": "P910", "hash": "bd9b993f710516ae8f0072dce66a6b4766dcd0a3", "datavalue": {"value": {"entity-type": "item", "numeric-id": 8973326, "id": "Q8973326"}, "type": "wikibase-entityid"}, "datatype": "wikibase-item"}, "type": "statement", "id": "Q41419$2E4FA8A5-8E39-4032-AA70-5E59C84680C8", "rank": "normal"}], "P646": [{"mainsnak": {"snaktype": "value", "property": "P646", "hash": "39df53ee94d4e43b2404d19e0e35ec40c1520852", "datavalue": {"value": "/m/095mj", "type": "string"}, "datatype": "external-id"}, "type": "statement", "id": "Q41419$51C03E63-990B-422D-ABDF-16534E4E228D", "rank": "normal", "references": [{"hash": "2b00cb481cddcac7623114367489b5c194901c4a", "snaks": {"P248": [{"snaktype": "value", "property": "P248", "hash": "a94b740202b097dd33355e0e6c00e54b9395e5e0", "datavalue": {"value": {"entity-type": "item", "numeric-id": 15241312, "id": "Q15241312"}, "type": "wikibase-entityid"}, "datatype": "wikibase-item"}], "P577": [{"snaktype": "value", "property": "P577", "hash": "fde79ecb015112d2f29229ccc1ec514ed3e71fa2", "datavalue": {"value": {"time": "+2013-10-28T00:00:00Z", "timezone": 0, "before": 0, "after": 0, "precision": 11, "calendarmodel": "http://www.wikidata.org/entity/Q1985727"}, "type": "time"}, "datatype": "time"}]}, "snaks-order": ["P248", "P577"]}]}], "P460": [{"mainsnak": {"snaktype": "value", "property": "P460", "hash": "cfd584891516a179b4c78748316a030bcbf78ff2", "datavalue": {"value": {"entity-type": "item", "numeric-id": 178710, "id": "Q178710"}, "type": "wikibase-entityid"}, "datatype": "wikibase-item"}, "type": "statement", "id": "Q41419$3F1B7CDC-ABD5-4033-B9AD-7D1FA7370F03", "rank": "normal", "references": [{"hash": "3bf39867b037e8e494a8389ae8a03bad6825a7fc", "snaks": {"P143": [{"snaktype": "value", "property": "P143", "hash": "5946b91c53409c48f5f1fb0319ed41fc67a764da", "datavalue": {"value": {"entity-type": "item", "numeric-id": 191168, "id": "Q191168"}, "type": "wikibase-entityid"}, "datatype": "wikibase-item"}]}, "snaks-order": ["P143"]}]}, {"mainsnak": {"snaktype": "value", "property": "P460", "hash": "f58339cbd3e83136dfe35822e612fdb71957449c", "datavalue": {"value": {"entity-type": "item", "numeric-id": 2052073, "id": "Q2052073"}, "type": "wikibase-entityid"}, "datatype": "wikibase-item"}, "type": "statement", "id": "Q41419$681f169b-4470-58c9-1f95-f50c4a9e174f", "rank": "normal"}, {"mainsnak": {"snaktype": "value", "property": "P460", "hash": "c69709990f783b9bc140301eb579e171b5131333", "datavalue": {"value": {"entity-type": "item", "numeric-id": 211611, "id": "Q211611"}, "type": "wikibase-entityid"}, "datatype": "wikibase-item"}, "type": "statement", "id": "Q41419$1871bab7-492e-2cb5-a2d0-5e23bf481c42", "rank": "normal"}], "P263": [{"mainsnak": {"snaktype": "value", "property": "P263", "hash": "340a8c524cf86c51e4772be0b7a50b13635865c5", "datavalue": {"value": {"entity-type": "item", "numeric-id": 70054479, "id": "Q70054479"}, "type": "wikibase-entityid"}, "datatype": "wikibase-item"}, "type": "statement", "id": "Q41419$386c7c9d-4505-18f1-a146-c89e12099268", "rank": "normal"}], "P1422": [{"mainsnak": {"snaktype": "value", "property": "P1422", "hash": "b17f79f65ec47c8442f977877bc016fed28d63cd", "datavalue": {"value": "5227", "type": "string"}, "datatype": "external-id"}, "type": "statement", "id": "Q41419$3073DFBE-F1E3-4C5B-BB9F-FCCE2E42F4A0", "rank": "normal"}], "P1049": [{"mainsnak": {"snaktype": "value", "property": "P1049", "hash": "3265296b9b83085b79de486bea57e11e7aff7766", "datavalue": {"value": {"entity-type": "item", "numeric-id": 855270, "id": "Q855270"}, "type": "wikibase-entityid"}, "datatype": "wikibase-item"}, "type": "statement", "id": "Q41419$6C025601-069A-42D1-85FB-8F0442C7B1FF", "rank": "normal"}], "P18": [{"mainsnak": {"snaktype": "value", "property": "P18", "hash": "16808d27fe5e19177043d9707dd82bfe1947755e", "datavalue": {"value": "Hestia - Wellesley College - DSC09634.JPG", "type": "string"}, "datatype": "commonsMedia"}, "type": "statement", "id": "Q41419$13293A5A-AA30-4FE4-9843-A3C8880BCE9C", "rank": "normal"}], "P1559": [{"mainsnak": {"snaktype": "value", "property": "P1559", "hash": "cde0bd60917753842c6c9f7f40cd901ba9ab0591", "datavalue": {"value": {"text": "\u1f19\u03c3\u03c4\u03af\u03b1", "language": "grc"}, "type": "monolingualtext"}, "datatype": "monolingualtext"}, "type": "statement", "id": "Q41419$b2beebfc-453a-8335-5958-3c86969b64c2", "rank": "normal"}, {"mainsnak": {"snaktype": "value", "property": "P1559", "hash": "ff0085409f9b1bc93e11d5b84449ce010ee711a8", "datavalue": {"value": {"text": "\u1f39\u03c3\u03c4\u03b9\u03b1", "language": "grc"}, "type": "monolingualtext"}, "datatype": "monolingualtext"}, "type": "statement", "id": "Q41419$a6ea8e2e-4bab-3bda-5840-99eca3b36155", "rank": "normal", "references": [{"hash": "5cdb262e52947b260042750060b6704cdfb728e7", "snaks": {"P3545": [{"snaktype": "value", "property": "P3545", "hash": "f3a63d1c696542af1a3712f2ece61e808286ee2d", "datavalue": {"value": "Ouranios/Hestia", "type": "string"}, "datatype": "external-id"}]}, "snaks-order": ["P3545"]}]}], "P3545": [{"mainsnak": {"snaktype": "value", "property": "P3545", "hash": "f3a63d1c696542af1a3712f2ece61e808286ee2d", "datavalue": {"value": "Ouranios/Hestia", "type": "string"}, "datatype": "external-id"}, "type": "statement", "id": "Q41419$83A69702-6715-48E9-94D8-F0D6DFDC3B15", "rank": "normal"}], "P1296": [{"mainsnak": {"snaktype": "value", "property": "P1296", "hash": "6744c496d7c4d738eac074acb629c603c7344862", "datavalue": {"value": "0032587", "type": "string"}, "datatype": "external-id"}, "type": "statement", "id": "Q41419$FF12B636-F9FC-4A9F-9CF6-1CBA2A89A2D7", "rank": "normal"}], "P2925": [{"mainsnak": {"snaktype": "value", "property": "P2925", "hash": "d5321d456125ae08d9ad47ca2329991c6437d0c4", "datavalue": {"value": {"entity-type": "item", "numeric-id": 585473, "id": "Q585473"}, "type": "wikibase-entityid"}, "datatype": "wikibase-item"}, "type": "statement", "id": "Q41419$80d824a4-4f8c-27ff-3cb6-a1689e80f49a", "rank": "normal", "references": [{"hash": "5cdb262e52947b260042750060b6704cdfb728e7", "snaks": {"P3545": [{"snaktype": "value", "property": "P3545", "hash": "f3a63d1c696542af1a3712f2ece61e808286ee2d", "datavalue": {"value": "Ouranios/Hestia", "type": "string"}, "datatype": "external-id"}]}, "snaks-order": ["P3545"]}]}, {"mainsnak": {"snaktype": "value", "property": "P2925", "hash": "05964c9b4408f36689e8a40678db8ff4585503d2", "datavalue": {"value": {"entity-type": "item", "numeric-id": 38695, "id": "Q38695"}, "type": "wikibase-entityid"}, "datatype": "wikibase-item"}, "type": "statement", "id": "Q41419$8b26c2a4-4ab8-1ace-3b2f-0936e78917a9", "rank": "normal", "references": [{"hash": "5cdb262e52947b260042750060b6704cdfb728e7", "snaks": {"P3545": [{"snaktype": "value", "property": "P3545", "hash": "f3a63d1c696542af1a3712f2ece61e808286ee2d", "datavalue": {"value": "Ouranios/Hestia", "type": "string"}, "datatype": "external-id"}]}, "snaks-order": ["P3545"]}]}, {"mainsnak": {"snaktype": "value", "property": "P2925", "hash": "859cd4b56b094e1d38c6cb2e4d129a81533bfe90", "datavalue": {"value": {"entity-type": "item", "numeric-id": 3196, "id": "Q3196"}, "type": "wikibase-entityid"}, "datatype": "wikibase-item"}, "type": "statement", "id": "Q41419$9cf9252d-4b3f-132c-1326-74324a2141c5", "rank": "normal", "references": [{"hash": "5cdb262e52947b260042750060b6704cdfb728e7", "snaks": {"P3545": [{"snaktype": "value", "property": "P3545", "hash": "f3a63d1c696542af1a3712f2ece61e808286ee2d", "datavalue": {"value": "Ouranios/Hestia", "type": "string"}, "datatype": "external-id"}]}, "snaks-order": ["P3545"]}]}, {"mainsnak": {"snaktype": "value", "property": "P2925", "hash": "6f6d06e43981a4c82ac433eb07fda4048cbe4b4f", "datavalue": {"value": {"entity-type": "item", "numeric-id": 720398, "id": "Q720398"}, "type": "wikibase-entityid"}, "datatype": "wikibase-item"}, "type": "statement", "id": "Q41419$c0cdae06-4911-2cf1-ff7e-d1066f623e2c", "rank": "normal", "references": [{"hash": "5cdb262e52947b260042750060b6704cdfb728e7", "snaks": {"P3545": [{"snaktype": "value", "property": "P3545", "hash": "f3a63d1c696542af1a3712f2ece61e808286ee2d", "datavalue": {"value": "Ouranios/Hestia", "type": "string"}, "datatype": "external-id"}]}, "snaks-order": ["P3545"]}]}, {"mainsnak": {"snaktype": "value", "property": "P2925", "hash": "3e245ede68fb37b36a0333b7abe373c4e4d18cac", "datavalue": {"value": {"entity-type": "item", "numeric-id": 699405, "id": "Q699405"}, "type": "wikibase-entityid"}, "datatype": "wikibase-item"}, "type": "statement", "id": "Q41419$84ea4afb-4f98-0732-83a1-92563efb6e89", "rank": "normal", "references": [{"hash": "5cdb262e52947b260042750060b6704cdfb728e7", "snaks": {"P3545": [{"snaktype": "value", "property": "P3545", "hash": "f3a63d1c696542af1a3712f2ece61e808286ee2d", "datavalue": {"value": "Ouranios/Hestia", "type": "string"}, "datatype": "external-id"}]}, "snaks-order": ["P3545"]}]}], "P4185": [{"mainsnak": {"snaktype": "value", "property": "P4185", "hash": "21840ee00f2aef38662ca6fe8c4eb192a7f94ad2", "datavalue": {"value": {"entity-type": "item", "numeric-id": 107444, "id": "Q107444"}, "type": "wikibase-entityid"}, "datatype": "wikibase-item"}, "type": "statement", "id": "Q41419$e3edf3bc-4599-1194-955f-34ad2b73b797", "rank": "normal", "references": [{"hash": "5cdb262e52947b260042750060b6704cdfb728e7", "snaks": {"P3545": [{"snaktype": "value", "property": "P3545", "hash": "f3a63d1c696542af1a3712f2ece61e808286ee2d", "datavalue": {"value": "Ouranios/Hestia", "type": "string"}, "datatype": "external-id"}]}, "snaks-order": ["P3545"]}]}, {"mainsnak": {"snaktype": "value", "property": "P4185", "hash": "88aa40c8dd146f7f4bd54b56cb0296e6d7924cd0", "datavalue": {"value": {"entity-type": "item", "numeric-id": 787, "id": "Q787"}, "type": "wikibase-entityid"}, "datatype": "wikibase-item"}, "type": "statement", "id": "Q41419$222eb830-4dc5-eb60-9d32-8b18c1d790cb", "rank": "normal", "references": [{"hash": "5cdb262e52947b260042750060b6704cdfb728e7", "snaks": {"P3545": [{"snaktype": "value", "property": "P3545", "hash": "f3a63d1c696542af1a3712f2ece61e808286ee2d", "datavalue": {"value": "Ouranios/Hestia", "type": "string"}, "datatype": "external-id"}]}, "snaks-order": ["P3545"]}]}, {"mainsnak": {"snaktype": "value", "property": "P4185", "hash": "dd5c7d2b1bd269fa57c3dc4ed7a5eea823cb496f", "datavalue": {"value": {"entity-type": "item", "numeric-id": 259318, "id": "Q259318"}, "type": "wikibase-entityid"}, "datatype": "wikibase-item"}, "type": "statement", "id": "Q41419$778e1242-444a-7744-49ce-742ccc3fa8ea", "rank": "normal", "references": [{"hash": "5cdb262e52947b260042750060b6704cdfb728e7", "snaks": {"P3545": [{"snaktype": "value", "property": "P3545", "hash": "f3a63d1c696542af1a3712f2ece61e808286ee2d", "datavalue": {"value": "Ouranios/Hestia", "type": "string"}, "datatype": "external-id"}]}, "snaks-order": ["P3545"]}]}], "P1971": [{"mainsnak": {"snaktype": "value", "property": "P1971", "hash": "37c7e2ccc275fd028792e682d6b88feac136f1e6", "datavalue": {"value": {"amount": "+0", "unit": "1"}, "type": "quantity"}, "datatype": "quantity"}, "type": "statement", "id": "Q41419$1abf6cee-404f-0085-ac62-4eeccafb3cac", "rank": "normal", "references": [{"hash": "5cdb262e52947b260042750060b6704cdfb728e7", "snaks": {"P3545": [{"snaktype": "value", "property": "P3545", "hash": "f3a63d1c696542af1a3712f2ece61e808286ee2d", "datavalue": {"value": "Ouranios/Hestia", "type": "string"}, "datatype": "external-id"}]}, "snaks-order": ["P3545"]}]}], "P3373": [{"mainsnak": {"snaktype": "value", "property": "P3373", "hash": "ee33f6ea720778b447b6bd97c5b1e41482fa1fa5", "datavalue": {"value": {"entity-type": "item", "numeric-id": 40730, "id": "Q40730"}, "type": "wikibase-entityid"}, "datatype": "wikibase-item"}, "type": "statement", "id": "Q41419$3bf6d191-4f89-1df0-4a0b-058abde62dfa", "rank": "normal", "references": [{"hash": "054aa68a54af6ff1a63dfcb342e47b87a3b349e6", "snaks": {"P854": [{"snaktype": "value", "property": "P854", "hash": "2bef98ff9a4f6b74159f1a18a4278d59a1cae7b7", "datavalue": {"value": "http://www.theoi.com/Tree5.html", "type": "string"}, "datatype": "url"}]}, "snaks-order": ["P854"]}]}, {"mainsnak": {"snaktype": "value", "property": "P3373", "hash": "fd917820ea45a6bc73ed6b2a13a51d24b84d8e36", "datavalue": {"value": {"entity-type": "item", "numeric-id": 38012, "id": "Q38012"}, "type": "wikibase-entityid"}, "datatype": "wikibase-item"}, "type": "statement", "id": "Q41419$de7febfb-4f2f-793a-e451-81c638d2a8a3", "rank": "normal", "references": [{"hash": "054aa68a54af6ff1a63dfcb342e47b87a3b349e6", "snaks": {"P854": [{"snaktype": "value", "property": "P854", "hash": "2bef98ff9a4f6b74159f1a18a4278d59a1cae7b7", "datavalue": {"value": "http://www.theoi.com/Tree5.html", "type": "string"}, "datatype": "url"}]}, "snaks-order": ["P854"]}]}, {"mainsnak": {"snaktype": "value", "property": "P3373", "hash": "81c8df82f741588a94737cfdbffd42997b594177", "datavalue": {"value": {"entity-type": "item", "numeric-id": 41410, "id": "Q41410"}, "type": "wikibase-entityid"}, "datatype": "wikibase-item"}, "type": "statement", "id": "Q41419$16f8bb17-410f-1802-11c0-b1b196cb81dd", "rank": "normal", "references": [{"hash": "054aa68a54af6ff1a63dfcb342e47b87a3b349e6", "snaks": {"P854": [{"snaktype": "value", "property": "P854", "hash": "2bef98ff9a4f6b74159f1a18a4278d59a1cae7b7", "datavalue": {"value": "http://www.theoi.com/Tree5.html", "type": "string"}, "datatype": "url"}]}, "snaks-order": ["P854"]}]}, {"mainsnak": {"snaktype": "value", "property": "P3373", "hash": "b33544e7a52755fb99225da4ee2697a72e3b7a83", "datavalue": {"value": {"entity-type": "item", "numeric-id": 41127, "id": "Q41127"}, "type": "wikibase-entityid"}, "datatype": "wikibase-item"}, "type": "statement", "id": "Q41419$cfe00469-4dcb-817c-c8b7-817cf2595263", "rank": "normal", "references": [{"hash": "054aa68a54af6ff1a63dfcb342e47b87a3b349e6", "snaks": {"P854": [{"snaktype": "value", "property": "P854", "hash": "2bef98ff9a4f6b74159f1a18a4278d59a1cae7b7", "datavalue": {"value": "http://www.theoi.com/Tree5.html", "type": "string"}, "datatype": "url"}]}, "snaks-order": ["P854"]}]}, {"mainsnak": {"snaktype": "value", "property": "P3373", "hash": "2748bbd625d927080261ca87e9d03eba092c1255", "datavalue": {"value": {"entity-type": "item", "numeric-id": 34201, "id": "Q34201"}, "type": "wikibase-entityid"}, "datatype": "wikibase-item"}, "type": "statement", "id": "Q41419$4685acdb-4f68-3b6e-73bf-99a17929fb95", "rank": "normal", "references": [{"hash": "054aa68a54af6ff1a63dfcb342e47b87a3b349e6", "snaks": {"P854": [{"snaktype": "value", "property": "P854", "hash": "2bef98ff9a4f6b74159f1a18a4278d59a1cae7b7", "datavalue": {"value": "http://www.theoi.com/Tree5.html", "type": "string"}, "datatype": "url"}]}, "snaks-order": ["P854"]}]}], "P361": [{"mainsnak": {"snaktype": "value", "property": "P361", "hash": "050d89a4e0f050fc521deea9ce05198cf4558b6e", "datavalue": {"value": {"entity-type": "item", "numeric-id": 101609, "id": "Q101609"}, "type": "wikibase-entityid"}, "datatype": "wikibase-item"}, "type": "statement", "id": "Q41419$4b82c164-401b-444a-1f53-1e6c958ac75f", "rank": "normal"}], "P1871": [{"mainsnak": {"snaktype": "value", "property": "P1871", "hash": "413fb821d3c4de5d69e90cacf80976baf8cde360", "datavalue": {"value": "cnp00552900", "type": "string"}, "datatype": "external-id"}, "type": "statement", "id": "Q41419$747552B0-0A96-4A0C-9264-526186FF3AB9", "rank": "normal"}], "P1417": [{"mainsnak": {"snaktype": "value", "property": "P1417", "hash": "6cfd34cdd6e1ec2c953b1139302ed38baf2514f7", "datavalue": {"value": "topic/Hestia", "type": "string"}, "datatype": "external-id"}, "type": "statement", "qualifiers": {"P1810": [{"snaktype": "value", "property": "P1810", "hash": "6f91f74be0c707527db6bddf3e057dda68f113aa", "datavalue": {"value": "Hestia", "type": "string"}, "datatype": "string"}]}, "qualifiers-order": ["P1810"], "id": "Q41419$85F5B27B-5E3C-48CA-B1B4-F8DA4056D9B9", "rank": "normal"}], "P214": [{"mainsnak": {"snaktype": "value", "property": "P214", "hash": "f3af1e45f50853b1b9bcd3d89ed3c43f2baadddd", "datavalue": {"value": "18028998", "type": "string"}, "datatype": "external-id"}, "type": "statement", "id": "Q41419$4BCB86D8-BAAB-410B-A64C-732A99CB7311", "rank": "normal", "references": [{"hash": "dd44a50a297d3fbbbfb86a9611a1e6862c067adb", "snaks": {"P248": [{"snaktype": "value", "property": "P248", "hash": "6b7d4330c4aac4caec4ede9de0311ce273f88ecd", "datavalue": {"value": {"entity-type": "item", "numeric-id": 54919, "id": "Q54919"}, "type": "wikibase-entityid"}, "datatype": "wikibase-item"}], "P214": [{"snaktype": "value", "property": "P214", "hash": "f3af1e45f50853b1b9bcd3d89ed3c43f2baadddd", "datavalue": {"value": "18028998", "type": "string"}, "datatype": "external-id"}], "P813": [{"snaktype": "value", "property": "P813", "hash": "a1b98b5c8bb6eca02829acaf6200c3e4a45b4dd0", "datavalue": {"value": {"time": "+2018-10-07T00:00:00Z", "timezone": 0, "before": 0, "after": 0, "precision": 11, "calendarmodel": "http://www.wikidata.org/entity/Q1985727"}, "type": "time"}, "datatype": "time"}]}, "snaks-order": ["P248", "P214", "P813"]}]}, {"mainsnak": {"snaktype": "value", "property": "P214", "hash": "afd9de121d3272f0dc27c346cb9edf03e5d03c3d", "datavalue": {"value": "205159012", "type": "string"}, "datatype": "external-id"}, "type": "statement", "id": "Q41419$7B89A8AA-7B9C-4A9A-BDCC-BC5084E359A8", "rank": "normal"}], "P244": [{"mainsnak": {"snaktype": "value", "property": "P244", "hash": "60a06ed8711c0d3000b56f787969fcaad81633fe", "datavalue": {"value": "no2016065482", "type": "string"}, "datatype": "external-id"}, "type": "statement", "id": "Q41419$ccf3681d-427b-5000-5d33-6b895714bb23", "rank": "normal", "references": [{"hash": "4071de3bbddb3d240288dd625487fbe2194fd132", "snaks": {"P248": [{"snaktype": "value", "property": "P248", "hash": "c120f07504c77593a9d734f50361ea829f601960", "datavalue": {"value": {"entity-type": "item", "numeric-id": 620946, "id": "Q620946"}, "type": "wikibase-entityid"}, "datatype": "wikibase-item"}], "P244": [{"snaktype": "value", "property": "P244", "hash": "60a06ed8711c0d3000b56f787969fcaad81633fe", "datavalue": {"value": "no2016065482", "type": "string"}, "datatype": "external-id"}], "P813": [{"snaktype": "value", "property": "P813", "hash": "987b0498788aa81ab8426846c113c4d9e2bb4a16", "datavalue": {"value": {"time": "+2019-02-18T00:00:00Z", "timezone": 0, "before": 0, "after": 0, "precision": 11, "calendarmodel": "http://www.wikidata.org/entity/Q1985727"}, "type": "time"}, "datatype": "time"}]}, "snaks-order": ["P248", "P244", "P813"]}]}], "P2163": [{"mainsnak": {"snaktype": "value", "property": "P2163", "hash": "eb977e37b3638a0bb3e6dd91f050740924af5b57", "datavalue": {"value": "955716", "type": "string"}, "datatype": "external-id"}, "type": "statement", "id": "Q41419$660d62a7-4b4b-71fc-7f7a-bd95114b727a", "rank": "normal"}], "P443": [{"mainsnak": {"snaktype": "value", "property": "P443", "hash": "f9e719bd9be4f28865099a06e560c07a5a0d0952", "datavalue": {"value": "LL-Q9129 (gre)-Ionenlaser-\u0395\u03c3\u03c4\u03af\u03b1.wav", "type": "string"}, "datatype": "commonsMedia"}, "type": "statement", "qualifiers": {"P407": [{"snaktype": "value", "property": "P407", "hash": "23e7ce4420e95fb6f17407e1e676202606c575f4", "datavalue": {"value": {"entity-type": "item", "numeric-id": 9129, "id": "Q9129"}, "type": "wikibase-entityid"}, "datatype": "wikibase-item"}]}, "qualifiers-order": ["P407"], "id": "Q41419$2705736f-0042-4d9c-bead-bd98184e63a7", "rank": "normal", "references": [{"hash": "5d83d4e82774fbae171b5374b378743d867522fa", "snaks": {"P854": [{"snaktype": "value", "property": "P854", "hash": "866a79f7698bfcb1365e1d6b9eee7ccdb0a148f8", "datavalue": {"value": "https://lingualibre.fr/wiki/Q104215", "type": "string"}, "datatype": "url"}]}, "snaks-order": ["P854"]}]}], "P949": [{"mainsnak": {"snaktype": "value", "property": "P949", "hash": "37b683f597b48d4df7e90553b0e9157084f64749", "datavalue": {"value": "000774929", "type": "string"}, "datatype": "external-id"}, "type": "statement", "id": "Q41419$4abb8c4b-4a9a-06c0-2b41-79cc85405e26", "rank": "normal"}], "P1343": [{"mainsnak": {"snaktype": "value", "property": "P1343", "hash": "30ae3c19e2efa0dd9fecc0501065766eae4e3d12", "datavalue": {"value": {"entity-type": "item", "numeric-id": 30059240, "id": "Q30059240"}, "type": "wikibase-entityid"}, "datatype": "wikibase-item"}, "type": "statement", "qualifiers": {"P805": [{"snaktype": "value", "property": "P805", "hash": "ead5df70bdc72bc2921d724f1072e709fd3777c3", "datavalue": {"value": {"entity-type": "item", "numeric-id": 45274233, "id": "Q45274233"}, "type": "wikibase-entityid"}, "datatype": "wikibase-item"}]}, "qualifiers-order": ["P805"], "id": "Q41419$a9816332-46b7-4abe-61a8-2fb3c650c7b5", "rank": "normal"}, {"mainsnak": {"snaktype": "value", "property": "P1343", "hash": "1e87e0f7d2db06ab0ef5ccabd7c6275641f36553", "datavalue": {"value": {"entity-type": "item", "numeric-id": 867541, "id": "Q867541"}, "type": "wikibase-entityid"}, "datatype": "wikibase-item"}, "type": "statement", "qualifiers": {"P805": [{"snaktype": "value", "property": "P805", "hash": "bdee777cdefd3f5262b70ad7fe5c4e0e3e892bb8", "datavalue": {"value": {"entity-type": "item", "numeric-id": 76511451, "id": "Q76511451"}, "type": "wikibase-entityid"}, "datatype": "wikibase-item"}]}, "qualifiers-order": ["P805"], "id": "Q41419$846ffa5d-46b5-dd60-6aa3-de152dcecf8e", "rank": "normal"}, {"mainsnak": {"snaktype": "value", "property": "P1343", "hash": "88389772f86dcd7d415ddd029f601412e5cc894a", "datavalue": {"value": {"entity-type": "item", "numeric-id": 602358, "id": "Q602358"}, "type": "wikibase-entityid"}, "datatype": "wikibase-item"}, "type": "statement", "qualifiers": {"P805": [{"snaktype": "value", "property": "P805", "hash": "cf343295b76e45f5aef3563346154739a7a4b569", "datavalue": {"value": {"entity-type": "item", "numeric-id": 24360852, "id": "Q24360852"}, "type": "wikibase-entityid"}, "datatype": "wikibase-item"}]}, "qualifiers-order": ["P805"], "id": "Q41419$c4b310ed-42e6-75e2-6ce2-0787c5739af6", "rank": "normal"}, {"mainsnak": {"snaktype": "value", "property": "P1343", "hash": "4cfd4eb1fe49d401455df557a7d9b1154f22a725", "datavalue": {"value": {"entity-type": "item", "numeric-id": 3181656, "id": "Q3181656"}, "type": "wikibase-entityid"}, "datatype": "wikibase-item"}, "type": "statement", "qualifiers": {"P1810": [{"snaktype": "value", "property": "P1810", "hash": "6f91f74be0c707527db6bddf3e057dda68f113aa", "datavalue": {"value": "Hestia", "type": "string"}, "datatype": "string"}]}, "qualifiers-order": ["P1810"], "id": "Q41419$0a1ab99c-48b6-299d-1a9d-79c374eac14b", "rank": "normal"}], "P2272": [{"mainsnak": {"snaktype": "value", "property": "P2272", "hash": "1e435ae9e8d76248f8d233a3916f75d9c68df38e", "datavalue": {"value": "Hestia", "type": "string"}, "datatype": "external-id"}, "type": "statement", "id": "Q41419$ED20854A-619E-4CA3-9C2C-CF02D596D328", "rank": "normal"}], "P5905": [{"mainsnak": {"snaktype": "value", "property": "P5905", "hash": "f241fd13e75f0b23ea90f278ec3a579befc609c8", "datavalue": {"value": "4005-10918", "type": "string"}, "datatype": "external-id"}, "type": "statement", "id": "Q41419$6B54E9AE-17D4-4EFF-B564-2E540E1B4331", "rank": "normal"}], "P4212": [{"mainsnak": {"snaktype": "value", "property": "P4212", "hash": "0e902c63b1f2ce8e05a5685c7a373243cdb7eee7", "datavalue": {"value": "pcrt1ejUdmu2Lq", "type": "string"}, "datatype": "external-id"}, "type": "statement", "id": "Q41419$779D6350-7E29-464E-9858-6A58C40008AE", "rank": "normal"}], "P269": [{"mainsnak": {"snaktype": "value", "property": "P269", "hash": "b6187261af2ed677db7bcf3f84faea21b4adf0b2", "datavalue": {"value": "150501757", "type": "string"}, "datatype": "external-id"}, "type": "statement", "id": "Q41419$9cf8fe0d-412c-a3cd-8bbe-0eef4f7a4b89", "rank": "normal"}], "P8408": [{"mainsnak": {"snaktype": "value", "property": "P8408", "hash": "aba7caae884355381573be64495c3fdf8ef06624", "datavalue": {"value": "Hestia-TheGoddess", "type": "string"}, "datatype": "external-id"}, "type": "statement", "id": "Q41419$844D5BFB-ADC9-45C8-8638-0F5277B89451", "rank": "normal", "references": [{"hash": "9a681f9dd95c90224547c404e11295f4f7dcf54e", "snaks": {"P248": [{"snaktype": "value", "property": "P248", "hash": "9d5780dddffa8746637a9929a936ab6b0f601e24", "datavalue": {"value": {"entity-type": "item", "numeric-id": 64139102, "id": "Q64139102"}, "type": "wikibase-entityid"}, "datatype": "wikibase-item"}], "P813": [{"snaktype": "value", "property": "P813", "hash": "622a5a27fa5b25e7e7984974e9db494cf8460990", "datavalue": {"value": {"time": "+2020-07-09T00:00:00Z", "timezone": 0, "before": 0, "after": 0, "precision": 11, "calendarmodel": "http://www.wikidata.org/entity/Q1985727"}, "type": "time"}, "datatype": "time"}]}, "snaks-order": ["P248", "P813"]}]}], "P268": [{"mainsnak": {"snaktype": "value", "property": "P268", "hash": "56d4f331db6301a441c0f86c3350e0793fbd5683", "datavalue": {"value": "16680586m", "type": "string"}, "datatype": "external-id"}, "type": "statement", "id": "Q41419$2F7E726B-4D99-48D2-851C-2DDB832BAAE3", "rank": "normal"}], "P5063": [{"mainsnak": {"snaktype": "value", "property": "P5063", "hash": "87772d15d2122a0fcb191893116e11cce5db79db", "datavalue": {"value": "i86919", "type": "string"}, "datatype": "external-id"}, "type": "statement", "id": "Q41419$0AC1ADE9-06D9-4F3B-B2FF-AC592A717728", "rank": "normal"}], "P3222": [{"mainsnak": {"snaktype": "value", "property": "P3222", "hash": "aa4c2d1c464b971d492e744b02ecdee129c26101", "datavalue": {"value": "hestia", "type": "string"}, "datatype": "external-id"}, "type": "statement", "id": "Q41419$3CB49EBE-CC02-47A8-94A8-2B152E6FD3B2", "rank": "normal"}], "P3417": [{"mainsnak": {"snaktype": "value", "property": "P3417", "hash": "861768ad87ad6c55ef4316d88672b51c959d7d4f", "datavalue": {"value": "Hestia-Greek-goddess", "type": "string"}, "datatype": "external-id"}, "type": "statement", "id": "Q41419$76D4BEE3-21F5-4438-8D8D-2E6777E99476", "rank": "normal"}], "P4342": [{"mainsnak": {"snaktype": "value", "property": "P4342", "hash": "40460f5e4b56ff6e10665a1376626a7d401fa15e", "datavalue": {"value": "Hestia", "type": "string"}, "datatype": "external-id"}, "type": "statement", "id": "Q41419$59BC37DD-CD0F-4761-9365-A9674F17A142", "rank": "normal"}], "P3569": [{"mainsnak": {"snaktype": "value", "property": "P3569", "hash": "79dc0495ca40d3391b8df2a8fbd300a9005710f0", "datavalue": {"value": "mythologie/hestia", "type": "string"}, "datatype": "external-id"}, "type": "statement", "id": "Q41419$44BEF4EB-3BFA-4C7F-96F0-8E5A99B3294C", "rank": "normal"}], "P7982": [{"mainsnak": {"snaktype": "value", "property": "P7982", "hash": "87f8244966ef690f5eac07327ea609789c302440", "datavalue": {"value": "25278", "type": "string"}, "datatype": "external-id"}, "type": "statement", "id": "Q41419$64FBF80B-D8F7-4EB7-B619-F027DC1020CB", "rank": "normal"}], "P8349": [{"mainsnak": {"snaktype": "value", "property": "P8349", "hash": "7d17016bff5bd48ea4f7fed913e06332db4cfefe", "datavalue": {"value": "26257", "type": "string"}, "datatype": "external-id"}, "type": "statement", "id": "Q41419$DD65B507-C4F3-43D3-96AE-8D53D27F4663", "rank": "normal"}], "P5019": [{"mainsnak": {"snaktype": "value", "property": "P5019", "hash": "18eacffc5cd669ee4396a22d913886c48d593165", "datavalue": {"value": "hestia", "type": "string"}, "datatype": "external-id"}, "type": "statement", "id": "Q41419$FF95890B-5DA2-4F75-871B-AEBB84E6689C", "rank": "normal"}], "P8669": [{"mainsnak": {"snaktype": "value", "property": "P8669", "hash": "d064f8902f3d441006fb2f27dffe797308a67e0e", "datavalue": {"value": "hestia", "type": "string"}, "datatype": "external-id"}, "type": "statement", "qualifiers": {"P1810": [{"snaktype": "value", "property": "P1810", "hash": "6f91f74be0c707527db6bddf3e057dda68f113aa", "datavalue": {"value": "Hestia", "type": "string"}, "datatype": "string"}], "P407": [{"snaktype": "value", "property": "P407", "hash": "44da625a3ae10060686d6729c546a67d4d69235f", "datavalue": {"value": {"entity-type": "item", "numeric-id": 9058, "id": "Q9058"}, "type": "wikibase-entityid"}, "datatype": "wikibase-item"}], "P577": [{"snaktype": "value", "property": "P577", "hash": "055be7178b5a4453af47b31639267f9c00f965b7", "datavalue": {"value": {"time": "+2008-02-00T00:00:00Z", "timezone": 0, "before": 0, "after": 0, "precision": 10, "calendarmodel": "http://www.wikidata.org/entity/Q1985727"}, "type": "time"}, "datatype": "time"}]}, "qualifiers-order": ["P1810", "P407", "P577"], "id": "Q41419$751BC36C-8C2D-4E4E-A732-80A5A1305EDD", "rank": "normal"}], "P9000": [{"mainsnak": {"snaktype": "value", "property": "P9000", "hash": "db25b6ac7f75345159dfe5385e488ddc9df84186", "datavalue": {"value": "Hestia", "type": "string"}, "datatype": "external-id"}, "type": "statement", "id": "Q41419$08D719CB-C69F-4E62-8E35-5A2947D7C05D", "rank": "normal"}], "P8814": [{"mainsnak": {"snaktype": "value", "property": "P8814", "hash": "a17918bdea61319c2b556c331fd8ec80e17bcdbd", "datavalue": {"value": "09587127-n", "type": "string"}, "datatype": "external-id"}, "type": "statement", "id": "Q41419$B68B961E-39F5-4517-86F3-8905FC13E4CB", "rank": "normal"}], "P9736": [{"mainsnak": {"snaktype": "value", "property": "P9736", "hash": "9612a00611bd393d4713da2c230eafccee599888", "datavalue": {"value": "8188391", "type": "string"}, "datatype": "external-id"}, "type": "statement", "id": "Q41419$0BA43965-25AD-4A85-86C0-EDF4D169F069", "rank": "normal"}], "P7305": [{"mainsnak": {"snaktype": "value", "property": "P7305", "hash": "5416a9efcbe66189a61fe876fdad0c62cd98410e", "datavalue": {"value": "3911443", "type": "string"}, "datatype": "external-id"}, "type": "statement", "id": "Q41419$A562AB2B-BAB8-4796-852B-E489CE9ED5EA", "rank": "normal"}], "P8189": [{"mainsnak": {"snaktype": "value", "property": "P8189", "hash": "64ce3f5baa512cb387574665ce920a0dabb14821", "datavalue": {"value": "987007546445605171", "type": "string"}, "datatype": "external-id"}, "type": "statement", "id": "Q41419$0DB7420C-B176-4A9B-9FDB-A717FD05CF6A", "rank": "normal"}], "P8313": [{"mainsnak": {"snaktype": "value", "property": "P8313", "hash": "66fb77067dfe68ec6d871a4fad08cbf54020ab9f", "datavalue": {"value": "Hestia", "type": "string"}, "datatype": "external-id"}, "type": "statement", "id": "Q41419$47C20D55-4A68-480D-86AC-B9623C16FB1C", "rank": "normal"}], "P8069": [{"mainsnak": {"snaktype": "value", "property": "P8069", "hash": "2c8acc19a574126999ade71857d90ddbedbb6eba", "datavalue": {"value": "325", "type": "string"}, "datatype": "external-id"}, "type": "statement", "id": "Q41419$FD825FE2-7013-4F80-B73F-EE92D3E7541B", "rank": "normal"}], "P10553": [{"mainsnak": {"snaktype": "value", "property": "P10553", "hash": "e835b328cf0a9b258215a4bb44c76aface19e4f6", "datavalue": {"value": "695973045", "type": "string"}, "datatype": "external-id"}, "type": "statement", "id": "Q41419$5423D850-DB08-4FA7-92C0-AD521AA4A6EB", "rank": "normal"}], "P6262": [{"mainsnak": {"snaktype": "value", "property": "P6262", "hash": "ab7ee15da3990629d014b1443418e09e55331210", "datavalue": {"value": "greekmythology:Hestia", "type": "string"}, "datatype": "external-id"}, "type": "statement", "qualifiers": {"P1810": [{"snaktype": "value", "property": "P1810", "hash": "6f91f74be0c707527db6bddf3e057dda68f113aa", "datavalue": {"value": "Hestia", "type": "string"}, "datatype": "string"}], "P407": [{"snaktype": "value", "property": "P407", "hash": "daf1c4fcb58181b02dff9cc89deb084004ddae4b", "datavalue": {"value": {"entity-type": "item", "numeric-id": 1860, "id": "Q1860"}, "type": "wikibase-entityid"}, "datatype": "wikibase-item"}], "P9675": [{"snaktype": "value", "property": "P9675", "hash": "f41cb6e8361cf7529907e15ea32d48f3c1afbcf0", "datavalue": {"value": "1927", "type": "string"}, "datatype": "string"}]}, "qualifiers-order": ["P1810", "P407", "P9675"], "id": "Q41419$FFF80F46-C854-4D0F-B173-5CAD06E999DA", "rank": "normal", "references": [{"hash": "1e70fa2177ec115c81acb9f36770f3f0066adcd4", "snaks": {"P854": [{"snaktype": "value", "property": "P854", "hash": "56ac13389c1aeda7ff0d4994a0b00bde55a66735", "datavalue": {"value": "https://greekmythology.fandom.com/wiki/Hestia", "type": "string"}, "datatype": "url"}], "P1476": [{"snaktype": "value", "property": "P1476", "hash": "13645cb0f6cfe991b74926e676e17cad21e04fcb", "datavalue": {"value": {"text": "Hestia | Greek Mythology Wiki | Fandom", "language": "en"}, "type": "monolingualtext"}, "datatype": "monolingualtext"}], "P813": [{"snaktype": "value", "property": "P813", "hash": "868a5f84b913175e0db9d501b79840eb8b9ff373", "datavalue": {"value": {"time": "+2022-07-15T00:00:00Z", "timezone": 0, "before": 0, "after": 0, "precision": 11, "calendarmodel": "http://www.wikidata.org/entity/Q1985727"}, "type": "time"}, "datatype": "time"}]}, "snaks-order": ["P854", "P1476", "P813"]}]}], "P6870": [{"mainsnak": {"snaktype": "value", "property": "P6870", "hash": "575328a2963c0bd3d18d149c5694bbab1bbdf21d", "datavalue": {"value": "150178", "type": "string"}, "datatype": "external-id"}, "type": "statement", "id": "Q41419$DC009AD1-F0BB-439E-B109-D52A997F6700", "rank": "normal"}], "P7502": [{"mainsnak": {"snaktype": "value", "property": "P7502", "hash": "66c45764f7f53039a392365cf5727b4f961d81ee", "datavalue": {"value": "Hestia-39KPP", "type": "string"}, "datatype": "external-id"}, "type": "statement", "id": "Q41419$D0D15BCB-749E-4F2D-8E94-DA98B3EDD371", "rank": "normal", "references": [{"hash": "1d6b44c9c159fcce57737c0a54ae2f498fe68a0f", "snaks": {"P813": [{"snaktype": "value", "property": "P813", "hash": "849bf31a75ee81eef52deceed6ee34b2f429e12c", "datavalue": {"value": {"time": "+2022-09-10T00:00:00Z", "timezone": 0, "before": 0, "after": 0, "precision": 11, "calendarmodel": "http://www.wikidata.org/entity/Q1985727"}, "type": "time"}, "datatype": "time"}], "P854": [{"snaktype": "value", "property": "P854", "hash": "08461cb1a8b440528dfa1f0ec6c47951c180f800", "datavalue": {"value": "https://golden.com/wiki/Hestia-39KPP", "type": "string"}, "datatype": "url"}]}, "snaks-order": ["P813", "P854"]}]}], "P5008": [{"mainsnak": {"snaktype": "value", "property": "P5008", "hash": "136e3fbe19158e73e4bfebf3f2d98a9df8638b7e", "datavalue": {"value": {"entity-type": "item", "numeric-id": 6173448, "id": "Q6173448"}, "type": "wikibase-entityid"}, "datatype": "wikibase-item"}, "type": "statement", "qualifiers": {"P585": [{"snaktype": "value", "property": "P585", "hash": "7661f66dd5b82a1ea92515ddb16c09ce3088edea", "datavalue": {"value": {"time": "+2022-10-31T00:00:00Z", "timezone": 0, "before": 0, "after": 0, "precision": 11, "calendarmodel": "http://www.wikidata.org/entity/Q1985727"}, "type": "time"}, "datatype": "time"}]}, "qualifiers-order": ["P585"], "id": "Q41419$CD46A1F4-1FE5-41DD-A273-9E503B1D6F44", "rank": "normal"}], "P1185": [{"mainsnak": {"snaktype": "value", "property": "P1185", "hash": "fb3dc404298430dec8e68f8d94e911dedd493de6", "datavalue": {"value": "26945", "type": "string"}, "datatype": "external-id"}, "type": "statement", "id": "Q41419$fd5b189e-6e64-4b0d-ae18-6729fe97a0f4", "rank": "normal"}], "P11946": [{"mainsnak": {"snaktype": "value", "property": "P11946", "hash": "924f12f516e02770152563ea24ff6f626501b6dd", "datavalue": {"value": "w25", "type": "string"}, "datatype": "external-id"}, "type": "statement", "id": "Q41419$2C12B051-BC2A-4DF1-8C40-049959C5771E", "rank": "normal", "references": [{"hash": "feeef550493b45b300f5fe3331f39415101b5036", "snaks": {"P248": [{"snaktype": "value", "property": "P248", "hash": "1b7c39810f08a2648ede6dbd9004d481dc892a73", "datavalue": {"value": {"entity-type": "item", "numeric-id": 120076891, "id": "Q120076891"}, "type": "wikibase-entityid"}, "datatype": "wikibase-item"}], "P11946": [{"snaktype": "value", "property": "P11946", "hash": "924f12f516e02770152563ea24ff6f626501b6dd", "datavalue": {"value": "w25", "type": "string"}, "datatype": "external-id"}], "P813": [{"snaktype": "value", "property": "P813", "hash": "1a291969e0eb6579bb3ecb1a5be87b6c6197e8d1", "datavalue": {"value": {"time": "+2023-08-15T00:00:00Z", "timezone": 0, "before": 0, "after": 0, "precision": 11, "calendarmodel": "http://www.wikidata.org/entity/Q1985727"}, "type": "time"}, "datatype": "time"}]}, "snaks-order": ["P248", "P11946", "P813"]}]}], "P1368": [{"mainsnak": {"snaktype": "value", "property": "P1368", "hash": "b108e66bb52ef24b5dd9ec7dc286ddc20e16f586", "datavalue": {"value": "000340271", "type": "string"}, "datatype": "external-id"}, "type": "statement", "id": "Q41419$cefac400-4378-cd14-ee1e-aea458302f9a", "rank": "normal"}], "P12086": [{"mainsnak": {"snaktype": "value", "property": "P12086", "hash": "d42c0f827387f05f8a41b3b6e7846a0aed2515f7", "datavalue": {"value": "Hestia_(mythologie)", "type": "string"}, "datatype": "external-id"}, "type": "statement", "id": "Q41419$16B87FB7-81C8-4D47-BCC4-700328464154", "rank": "normal"}], "P12385": [{"mainsnak": {"snaktype": "value", "property": "P12385", "hash": "9a944b97f0169798a5bfbb4af2c7fa6fead30e12", "datavalue": {"value": "hestia", "type": "string"}, "datatype": "external-id"}, "type": "statement", "id": "Q41419$905471ac-6eda-42f0-b738-215cf76c6368", "rank": "normal"}], "P12467": [{"mainsnak": {"snaktype": "value", "property": "P12467", "hash": "cf87df917d17d1b3e92df394a7a0266bbe548012", "datavalue": {"value": "120", "type": "string"}, "datatype": "external-id"}, "type": "statement", "id": "Q41419$6A25A853-A489-465F-895E-EABF1EEA5826", "rank": "normal"}], "P12800": [{"mainsnak": {"snaktype": "value", "property": "P12800", "hash": "167c1768497946c5e358bb7a991e85422b551b33", "datavalue": {"value": "fr:Hestia", "type": "string"}, "datatype": "external-id"}, "type": "statement", "id": "Q41419$FFCF0963-43D0-4877-AC58-E1DF39E95B1B", "rank": "normal"}], "P451": [{"mainsnak": {"snaktype": "value", "property": "P451", "hash": "50a68c2c3e2e2b53e3d233d0d397e3b971c5c354", "datavalue": {"value": {"entity-type": "item", "numeric-id": 206878, "id": "Q206878"}, "type": "wikibase-entityid"}, "datatype": "wikibase-item"}, "type": "statement", "qualifiers": {"P2241": [{"snaktype": "value", "property": "P2241", "hash": "c85678e79e70a5bb2dea3ed95357e634170163db", "datavalue": {"value": {"entity-type": "item", "numeric-id": 52237215, "id": "Q52237215"}, "type": "wikibase-entityid"}, "datatype": "wikibase-item"}]}, "qualifiers-order": ["P2241"], "id": "Q41419$e0398d40-429a-981c-d94c-7ee335d5f349", "rank": "deprecated", "references": [{"hash": "5006e4bf1235594cbe1ba3738bc137caac97b8c9", "snaks": {"P248": [{"snaktype": "value", "property": "P248", "hash": "07b085e9a73b129fb688b04dbf9de640bd8045d2", "datavalue": {"value": {"entity-type": "item", "numeric-id": 18387659, "id": "Q18387659"}, "type": "wikibase-entityid"}, "datatype": "wikibase-item"}]}, "snaks-order": ["P248"]}]}], "P13049": [{"mainsnak": {"snaktype": "value", "property": "P13049", "hash": "c44e873d00e7f281adb6fac779631885470c93f8", "datavalue": {"value": "119320657", "type": "string"}, "datatype": "external-id"}, "type": "statement", "id": "Q41419$23DDA3C3-B36E-4B73-80B6-CE900CDB1889", "rank": "normal"}], "P13094": [{"mainsnak": {"snaktype": "value", "property": "P13094", "hash": "1c521c95c69824da6456108403ffdd100455d1cb", "datavalue": {"value": "YUaT4Sd6S5qR658RzAwoAge", "type": "string"}, "datatype": "external-id"}, "type": "statement", "id": "Q41419$29375105-FDD1-4922-9FF4-823946EC4D74", "rank": "normal"}], "P3365": [{"mainsnak": {"snaktype": "value", "property": "P3365", "hash": "3cb7345f4bf77b8645df0e4aa731e04804085d05", "datavalue": {"value": "estia", "type": "string"}, "datatype": "external-id"}, "type": "statement", "qualifiers": {"P1810": [{"snaktype": "value", "property": "P1810", "hash": "f68a89dbc38019ef228be6d1e072011379aaa240", "datavalue": {"value": "Estia", "type": "string"}, "datatype": "string"}]}, "qualifiers-order": ["P1810"], "id": "Q41419$2ef73173-41de-59b1-1ae3-e3f396508093", "rank": "normal"}], "P4223": [{"mainsnak": {"snaktype": "value", "property": "P4223", "hash": "cfe07d392ec386bb14faab64e0bfa039271c41e9", "datavalue": {"value": "estia", "type": "string"}, "datatype": "external-id"}, "type": "statement", "qualifiers": {"P1810": [{"snaktype": "value", "property": "P1810", "hash": "10fffc618cd30ebc102cc88bba137e633457a736", "datavalue": {"value": "ESTIA", "type": "string"}, "datatype": "string"}], "P50": [{"snaktype": "value", "property": "P50", "hash": "b1e1e90635428835dc67d98e2162e88ae83ae3e1", "datavalue": {"value": {"entity-type": "item", "numeric-id": 3769662, "id": "Q3769662"}, "type": "wikibase-entityid"}, "datatype": "wikibase-item"}], "P577": [{"snaktype": "value", "property": "P577", "hash": "e141ecb72f98adb303d7e381370d473d50bf8269", "datavalue": {"value": {"time": "+1932-00-00T00:00:00Z", "timezone": 0, "before": 0, "after": 0, "precision": 9, "calendarmodel": "http://www.wikidata.org/entity/Q1985727"}, "type": "time"}, "datatype": "time"}]}, "qualifiers-order": ["P1810", "P50", "P577"], "id": "Q41419$5cfe392e-42eb-ff07-4b17-dd5e5c0330f1", "rank": "normal"}], "P9809": [{"mainsnak": {"snaktype": "value", "property": "P9809", "hash": "a2c550ff1c2753025a442bed692d8d7168072ad2", "datavalue": {"value": "hestia", "type": "string"}, "datatype": "external-id"}, "type": "statement", "qualifiers": {"P1810": [{"snaktype": "value", "property": "P1810", "hash": "727cc400f33b7938de0687fdf9859dd38ecf7766", "datavalue": {"value": "HESTIA", "type": "string"}, "datatype": "string"}], "P2093": [{"snaktype": "value", "property": "P2093", "hash": "4b27cea683f390b97d2bb3f8d9d203718db7dccd", "datavalue": {"value": "W. Fuchs", "type": "string"}, "datatype": "string"}], "P577": [{"snaktype": "value", "property": "P577", "hash": "08a21a4113ada32bbd1868f5ac382a39ceaa1ec7", "datavalue": {"value": {"time": "+1961-00-00T00:00:00Z", "timezone": 0, "before": 0, "after": 0, "precision": 9, "calendarmodel": "http://www.wikidata.org/entity/Q1985727"}, "type": "time"}, "datatype": "time"}]}, "qualifiers-order": ["P1810", "P2093", "P577"], "id": "Q41419$4f496657-4186-71dd-7c0d-8bf39e02a566", "rank": "normal"}], "P6706": [{"mainsnak": {"snaktype": "value", "property": "P6706", "hash": "924c747f75e325b03015abe3015f4a611e84907f", "datavalue": {"value": "Est\u00eca", "type": "string"}, "datatype": "external-id"}, "type": "statement", "qualifiers": {"P1810": [{"snaktype": "value", "property": "P1810", "hash": "14dc3b670c65a7bcb17cd638e002231b1ad680b9", "datavalue": {"value": "Est\u00eca", "type": "string"}, "datatype": "string"}]}, "qualifiers-order": ["P1810"], "id": "Q41419$0768c31b-4981-ff4e-dc4b-8c519f2f0d67", "rank": "normal"}], "P3847": [{"mainsnak": {"snaktype": "value", "property": "P3847", "hash": "481b168bdf3e0342847f81058a20a6ad3b39dac9", "datavalue": {"value": "hestia_(greek_deity)", "type": "string"}, "datatype": "external-id"}, "type": "statement", "qualifiers": {"P1810": [{"snaktype": "value", "property": "P1810", "hash": "80fb31e502d5d66c2d42dbfbdcac49a51519f0a7", "datavalue": {"value": "Hestia (Greek deity)", "type": "string"}, "datatype": "string"}]}, "qualifiers-order": ["P1810"], "id": "Q41419$93f37a10-4b4d-db78-11fe-1e2808645d0b", "rank": "normal"}], "P10757": [{"mainsnak": {"snaktype": "value", "property": "P10757", "hash": "5e99bc69b7d9192fe31f717e5aa6e0876d525a34", "datavalue": {"value": "5190", "type": "string"}, "datatype": "external-id"}, "type": "statement", "id": "Q41419$0c0f0432-45a0-0942-9043-9e281a39127b", "rank": "normal"}], "P13591": [{"mainsnak": {"snaktype": "value", "property": "P13591", "hash": "9435f6176175d83007ef40509be50edd3f9d00da", "datavalue": {"value": "concept/31c10de0-2af6-4dda-8f52-73273fea90b0", "type": "string"}, "datatype": "external-id"}, "type": "statement", "id": "Q41419$447792D1-0AC5-46FE-ADE5-5FC1BFD8C4B6", "rank": "normal"}]}, "sitelinks": {"afwiki": {"site": "afwiki", "title": "Hestia", "badges": [], "url": "https://af.wikipedia.org/wiki/Hestia"}, "anwiki": {"site": "anwiki", "title": "Hestia", "badges": [], "url": "https://an.wikipedia.org/wiki/Hestia"}, "arwiki": {"site": "arwiki", "title": "\u0647\u064a\u0633\u062a\u064a\u0627", "badges": [], "url": "https://ar.wikipedia.org/wiki/%D9%87%D9%8A%D8%B3%D8%AA%D9%8A%D8%A7"}, "arzwiki": {"site": "arzwiki", "title": "\u0647\u064a\u0633\u062a\u064a\u0627", "badges": [], "url": "https://arz.wikipedia.org/wiki/%D9%87%D9%8A%D8%B3%D8%AA%D9%8A%D8%A7"}, "astwiki": {"site": "astwiki", "title": "Hestia", "badges": [], "url": "https://ast.wikipedia.org/wiki/Hestia"}, "aswiki": {"site": "aswiki", "title": "\u09b9\u09c7\u09b7\u09cd\u099f\u09bf\u09af\u09bc\u09be", "badges": [], "url": "https://as.wikipedia.org/wiki/%E0%A6%B9%E0%A7%87%E0%A6%B7%E0%A7%8D%E0%A6%9F%E0%A6%BF%E0%A6%AF%E0%A6%BC%E0%A6%BE"}, "azwiki": {"site": "azwiki", "title": "Hestiya", "badges": [], "url": "https://az.wikipedia.org/wiki/Hestiya"}, "barwiki": {"site": "barwiki", "title": "Hestia", "badges": [], "url": "https://bar.wikipedia.org/wiki/Hestia"}, "bclwiki": {"site": "bclwiki", "title": "Hestia", "badges": [], "url": "https://bcl.wikipedia.org/wiki/Hestia"}, "be_x_oldwiki": {"site": "be_x_oldwiki", "title": "\u0413\u0435\u0441\u0442\u044b\u044f", "badges": [], "url": "https://be-tarask.wikipedia.org/wiki/%D0%93%D0%B5%D1%81%D1%82%D1%8B%D1%8F"}, "bewiki": {"site": "bewiki", "title": "\u0413\u0435\u0441\u0442\u044b\u044f", "badges": [], "url": "https://be.wikipedia.org/wiki/%D0%93%D0%B5%D1%81%D1%82%D1%8B%D1%8F"}, "bgwiki": {"site": "bgwiki", "title": "\u0425\u0435\u0441\u0442\u0438\u044f", "badges": [], "url": "https://bg.wikipedia.org/wiki/%D0%A5%D0%B5%D1%81%D1%82%D0%B8%D1%8F"}, "bnwiki": {"site": "bnwiki", "title": "\u09b9\u09c7\u09b8\u09cd\u09a4\u09bf\u09af\u09bc\u09be", "badges": [], "url": "https://bn.wikipedia.org/wiki/%E0%A6%B9%E0%A7%87%E0%A6%B8%E0%A7%8D%E0%A6%A4%E0%A6%BF%E0%A6%AF%E0%A6%BC%E0%A6%BE"}, "brwiki": {"site": "brwiki", "title": "Hestia", "badges": [], "url": "https://br.wikipedia.org/wiki/Hestia"}, "bswiki": {"site": "bswiki", "title": "Hestija", "badges": [], "url": "https://bs.wikipedia.org/wiki/Hestija"}, "cawiki": {"site": "cawiki", "title": "H\u00e8stia", "badges": [], "url": "https://ca.wikipedia.org/wiki/H%C3%A8stia"}, "cswiki": {"site": "cswiki", "title": "Hestia", "badges": [], "url": "https://cs.wikipedia.org/wiki/Hestia"}, "cywiki": {"site": "cywiki", "title": "Hestia", "badges": [], "url": "https://cy.wikipedia.org/wiki/Hestia"}, "dawiki": {"site": "dawiki", "title": "Hestia", "badges": [], "url": "https://da.wikipedia.org/wiki/Hestia"}, "dewiki": {"site": "dewiki", "title": "Hestia", "badges": [], "url": "https://de.wikipedia.org/wiki/Hestia"}, "elwiki": {"site": "elwiki", "title": "\u0395\u03c3\u03c4\u03af\u03b1 (\u03bc\u03c5\u03b8\u03bf\u03bb\u03bf\u03b3\u03af\u03b1)", "badges": [], "url": "https://el.wikipedia.org/wiki/%CE%95%CF%83%CF%84%CE%AF%CE%B1_(%CE%BC%CF%85%CE%B8%CE%BF%CE%BB%CE%BF%CE%B3%CE%AF%CE%B1)"}, "enwiki": {"site": "enwiki", "title": "Hestia", "badges": [], "url": "https://en.wikipedia.org/wiki/Hestia"}, "eowiki": {"site": "eowiki", "title": "Hestia", "badges": [], "url": "https://eo.wikipedia.org/wiki/Hestia"}, "eswiki": {"site": "eswiki", "title": "Hestia", "badges": [], "url": "https://es.wikipedia.org/wiki/Hestia"}, "etwiki": {"site": "etwiki", "title": "Hestia", "badges": [], "url": "https://et.wikipedia.org/wiki/Hestia"}, "euwiki": {"site": "euwiki", "title": "Hestia", "badges": [], "url": "https://eu.wikipedia.org/wiki/Hestia"}, "fawiki": {"site": "fawiki", "title": "\u0647\u0633\u062a\u06cc\u0627", "badges": [], "url": "https://fa.wikipedia.org/wiki/%D9%87%D8%B3%D8%AA%DB%8C%D8%A7"}, "fiwiki": {"site": "fiwiki", "title": "Hestia", "badges": [], "url": "https://fi.wikipedia.org/wiki/Hestia"}, "frwiki": {"site": "frwiki", "title": "Hestia", "badges": [], "url": "https://fr.wikipedia.org/wiki/Hestia"}, "frwikibooks": {"site": "frwikibooks", "title": "Grec ancien/Dieux/Hestia", "badges": [], "url": "https://fr.wikibooks.org/wiki/Grec_ancien/Dieux/Hestia"}, "frwikiquote": {"site": "frwikiquote", "title": "Hestia", "badges": [], "url": "https://fr.wikiquote.org/wiki/Hestia"}, "gawiki": {"site": "gawiki", "title": "Heistia", "badges": [], "url": "https://ga.wikipedia.org/wiki/Heistia"}, "glwiki": {"site": "glwiki", "title": "Hestia (deusa)", "badges": [], "url": "https://gl.wikipedia.org/wiki/Hestia_(deusa)"}, "hewiki": {"site": "hewiki", "title": "\u05d4\u05e1\u05d8\u05d9\u05d4", "badges": [], "url": "https://he.wikipedia.org/wiki/%D7%94%D7%A1%D7%98%D7%99%D7%94"}, "hiwiki": {"site": "hiwiki", "title": "\u0939\u0947\u0938\u094d\u091f\u093f\u092f\u093e", "badges": [], "url": "https://hi.wikipedia.org/wiki/%E0%A4%B9%E0%A5%87%E0%A4%B8%E0%A5%8D%E0%A4%9F%E0%A4%BF%E0%A4%AF%E0%A4%BE"}, "hrwiki": {"site": "hrwiki", "title": "Hestija", "badges": [], "url": "https://hr.wikipedia.org/wiki/Hestija"}, "huwiki": {"site": "huwiki", "title": "Hesztia", "badges": [], "url": "https://hu.wikipedia.org/wiki/Hesztia"}, "hywiki": {"site": "hywiki", "title": "\u0540\u0565\u057d\u057f\u056b\u0561", "badges": [], "url": "https://hy.wikipedia.org/wiki/%D5%80%D5%A5%D5%BD%D5%BF%D5%AB%D5%A1"}, "iawiki": {"site": "iawiki", "title": "Hestia", "badges": [], "url": "https://ia.wikipedia.org/wiki/Hestia"}, "idwiki": {"site": "idwiki", "title": "Hestia", "badges": [], "url": "https://id.wikipedia.org/wiki/Hestia"}, "iowiki": {"site": "iowiki", "title": "Hestia", "badges": [], "url": "https://io.wikipedia.org/wiki/Hestia"}, "itwiki": {"site": "itwiki", "title": "Estia", "badges": [], "url": "https://it.wikipedia.org/wiki/Estia"}, "jawiki": {"site": "jawiki", "title": "\u30d8\u30b9\u30c6\u30a3\u30a2\u30fc", "badges": [], "url": "https://ja.wikipedia.org/wiki/%E3%83%98%E3%82%B9%E3%83%86%E3%82%A3%E3%82%A2%E3%83%BC"}, "jvwiki": {"site": "jvwiki", "title": "Hestia", "badges": [], "url": "https://jv.wikipedia.org/wiki/Hestia"}, "kawiki": {"site": "kawiki", "title": "\u10f0\u10d4\u10e1\u10e2\u10d8\u10d0", "badges": [], "url": "https://ka.wikipedia.org/wiki/%E1%83%B0%E1%83%94%E1%83%A1%E1%83%A2%E1%83%98%E1%83%90"}, "kkwiki": {"site": "kkwiki", "title": "\u0413\u0435\u0441\u0442\u0438\u044f", "badges": [], "url": "https://kk.wikipedia.org/wiki/%D0%93%D0%B5%D1%81%D1%82%D0%B8%D1%8F"}, "kowiki": {"site": "kowiki", "title": "\ud5e4\uc2a4\ud2f0\uc544", "badges": [], "url": "https://ko.wikipedia.org/wiki/%ED%97%A4%EC%8A%A4%ED%8B%B0%EC%95%84"}, "kuwiki": {"site": "kuwiki", "title": "Hest\u00eea", "badges": [], "url": "https://ku.wikipedia.org/wiki/Hest%C3%AEa"}, "lawiki": {"site": "lawiki", "title": "Hestia", "badges": [], "url": "https://la.wikipedia.org/wiki/Hestia"}, "lbwiki": {"site": "lbwiki", "title": "Hestia", "badges": [], "url": "https://lb.wikipedia.org/wiki/Hestia"}, "lfnwiki": {"site": "lfnwiki", "title": "Hestia", "badges": [], "url": "https://lfn.wikipedia.org/wiki/Hestia"}, "ltwiki": {"site": "ltwiki", "title": "Hestija", "badges": [], "url": "https://lt.wikipedia.org/wiki/Hestija"}, "lvwiki": {"site": "lvwiki", "title": "Hestija", "badges": [], "url": "https://lv.wikipedia.org/wiki/Hestija"}, "mkwiki": {"site": "mkwiki", "title": "\u0425\u0435\u0441\u0442\u0438\u0458\u0430", "badges": [], "url": "https://mk.wikipedia.org/wiki/%D0%A5%D0%B5%D1%81%D1%82%D0%B8%D1%98%D0%B0"}, "mlwiki": {"site": "mlwiki", "title": "\u0d39\u0d46\u0d38\u0d4d\u0d31\u0d4d\u0d31\u0d3f\u0d2f", "badges": [], "url": "https://ml.wikipedia.org/wiki/%E0%B4%B9%E0%B5%86%E0%B4%B8%E0%B5%8D%E0%B4%B1%E0%B5%8D%E0%B4%B1%E0%B4%BF%E0%B4%AF"}, "mniwiki": {"site": "mniwiki", "title": "\uabcd\uabe6\uabc1\uabed\uabc7\uabe4\uabcc\uabe5", "badges": [], "url": "https://mni.wikipedia.org/wiki/%EA%AF%8D%EA%AF%A6%EA%AF%81%EA%AF%AD%EA%AF%87%EA%AF%A4%EA%AF%8C%EA%AF%A5"}, "mrwiki": {"site": "mrwiki", "title": "\u0939\u0947\u0938\u094d\u0924\u093f\u092f\u093e", "badges": [], "url": "https://mr.wikipedia.org/wiki/%E0%A4%B9%E0%A5%87%E0%A4%B8%E0%A5%8D%E0%A4%A4%E0%A4%BF%E0%A4%AF%E0%A4%BE"}, "mswiki": {"site": "mswiki", "title": "Hestia", "badges": [], "url": "https://ms.wikipedia.org/wiki/Hestia"}, "mznwiki": {"site": "mznwiki", "title": "\u0647\u0633\u062a\u06cc\u0627", "badges": [], "url": "https://mzn.wikipedia.org/wiki/%D9%87%D8%B3%D8%AA%DB%8C%D8%A7"}, "ndswiki": {"site": "ndswiki", "title": "Hestia", "badges": [], "url": "https://nds.wikipedia.org/wiki/Hestia"}, "nlwiki": {"site": "nlwiki", "title": "Hestia (mythologie)", "badges": [], "url": "https://nl.wikipedia.org/wiki/Hestia_(mythologie)"}, "nnwiki": {"site": "nnwiki", "title": "Hestia", "badges": [], "url": "https://nn.wikipedia.org/wiki/Hestia"}, "nowiki": {"site": "nowiki", "title": "Hestia", "badges": [], "url": "https://no.wikipedia.org/wiki/Hestia"}, "ocwiki": {"site": "ocwiki", "title": "Estia", "badges": [], "url": "https://oc.wikipedia.org/wiki/Estia"}, "pawiki": {"site": "pawiki", "title": "\u0a39\u0a47\u0a38\u0a1f\u0a40\u0a06", "badges": [], "url": "https://pa.wikipedia.org/wiki/%E0%A8%B9%E0%A9%87%E0%A8%B8%E0%A8%9F%E0%A9%80%E0%A8%86"}, "plwiki": {"site": "plwiki", "title": "Hestia", "badges": [], "url": "https://pl.wikipedia.org/wiki/Hestia"}, "pnbwiki": {"site": "pnbwiki", "title": "\u06c1\u06cc\u0633\u0679\u06cc\u06c1", "badges": [], "url": "https://pnb.wikipedia.org/wiki/%DB%81%DB%8C%D8%B3%D9%B9%DB%8C%DB%81"}, "ptwiki": {"site": "ptwiki", "title": "H\u00e9stia", "badges": [], "url": "https://pt.wikipedia.org/wiki/H%C3%A9stia"}, "rowiki": {"site": "rowiki", "title": "Hestia", "badges": [], "url": "https://ro.wikipedia.org/wiki/Hestia"}, "ruwiki": {"site": "ruwiki", "title": "\u0413\u0435\u0441\u0442\u0438\u044f", "badges": [], "url": "https://ru.wikipedia.org/wiki/%D0%93%D0%B5%D1%81%D1%82%D0%B8%D1%8F"}, "shwiki": {"site": "shwiki", "title": "Hestija", "badges": [], "url": "https://sh.wikipedia.org/wiki/Hestija"}, "simplewiki": {"site": "simplewiki", "title": "Hestia", "badges": [], "url": "https://simple.wikipedia.org/wiki/Hestia"}, "skwiki": {"site": "skwiki", "title": "Hestia", "badges": [], "url": "https://sk.wikipedia.org/wiki/Hestia"}, "slwiki": {"site": "slwiki", "title": "Hestija", "badges": [], "url": "https://sl.wikipedia.org/wiki/Hestija"}, "sqwiki": {"site": "sqwiki", "title": "Hestia", "badges": [], "url": "https://sq.wikipedia.org/wiki/Hestia"}, "srwiki": {"site": "srwiki", "title": "\u0425\u0435\u0441\u0442\u0438\u0458\u0430", "badges": [], "url": "https://sr.wikipedia.org/wiki/%D0%A5%D0%B5%D1%81%D1%82%D0%B8%D1%98%D0%B0"}, "svwiki": {"site": "svwiki", "title": "Hestia", "badges": [], "url": "https://sv.wikipedia.org/wiki/Hestia"}, "swwiki": {"site": "swwiki", "title": "Hestia", "badges": [], "url": "https://sw.wikipedia.org/wiki/Hestia"}, "tawiki": {"site": "tawiki", "title": "\u0b8e\u0b9a\u0bbf\u0b9f\u0bbf\u0baf\u0bbe", "badges": [], "url": "https://ta.wikipedia.org/wiki/%E0%AE%8E%E0%AE%9A%E0%AE%BF%E0%AE%9F%E0%AE%BF%E0%AE%AF%E0%AE%BE"}, "thwiki": {"site": "thwiki", "title": "\u0e40\u0e2e\u0e2a\u0e40\u0e15\u0e35\u0e22", "badges": [], "url": "https://th.wikipedia.org/wiki/%E0%B9%80%E0%B8%AE%E0%B8%AA%E0%B9%80%E0%B8%95%E0%B8%B5%E0%B8%A2"}, "tlwiki": {"site": "tlwiki", "title": "Hestia", "badges": [], "url": "https://tl.wikipedia.org/wiki/Hestia"}, "trwiki": {"site": "trwiki", "title": "Hestia", "badges": [], "url": "https://tr.wikipedia.org/wiki/Hestia"}, "ttwiki": {"site": "ttwiki", "title": "Hesti\u00e4", "badges": [], "url": "https://tt.wikipedia.org/wiki/Hesti%C3%A4"}, "ukwiki": {"site": "ukwiki", "title": "\u0413\u0435\u0441\u0442\u0456\u044f", "badges": [], "url": "https://uk.wikipedia.org/wiki/%D0%93%D0%B5%D1%81%D1%82%D1%96%D1%8F"}, "urwiki": {"site": "urwiki", "title": "\u06c1\u06cc\u0633\u0679\u06cc\u06c1", "badges": [], "url": "https://ur.wikipedia.org/wiki/%DB%81%DB%8C%D8%B3%D9%B9%DB%8C%DB%81"}, "uzwiki": {"site": "uzwiki", "title": "Xestiya", "badges": [], "url": "https://uz.wikipedia.org/wiki/Xestiya"}, "vepwiki": {"site": "vepwiki", "title": "Gestija", "badges": [], "url": "https://vep.wikipedia.org/wiki/Gestija"}, "viwiki": {"site": "viwiki", "title": "Hestia", "badges": [], "url": "https://vi.wikipedia.org/wiki/Hestia"}, "warwiki": {"site": "warwiki", "title": "Hestia", "badges": [], "url": "https://war.wikipedia.org/wiki/Hestia"}, "wuuwiki": {"site": "wuuwiki", "title": "\u8d6b\u65af\u63d0\u4e9a", "badges": [], "url": "https://wuu.wikipedia.org/wiki/%E8%B5%AB%E6%96%AF%E6%8F%90%E4%BA%9A"}, "zh_min_nanwiki": {"site": "zh_min_nanwiki", "title": "Hestia", "badges": [], "url": "https://zh-min-nan.wikipedia.org/wiki/Hestia"}, "zh_yuewiki": {"site": "zh_yuewiki", "title": "\u5e0c\u5f0f\u9435", "badges": [], "url": "https://zh-yue.wikipedia.org/wiki/%E5%B8%8C%E5%BC%8F%E9%90%B5"}, "zhwiki": {"site": "zhwiki", "title": "\u8d6b\u65af\u63d0\u4e9e", "badges": [], "url": "https://zh.wikipedia.org/wiki/%E8%B5%AB%E6%96%AF%E6%8F%90%E4%BA%9E"}}}}}